{
  "$schema": "https://typedoc.org/schema.json",
  "entryPoints": [
    "packages/shared/src/index.ts",
    "packages/domain/src/index.ts",
    "packages/infrastructure/src/index.ts",
    "packages/application/src/index.ts"
  ],
  "entryPointStrategy": "expand",
  "out": "docs/api",
  "readme": "none",
  "githubPages": false,
  "excludePrivate": true,
  "excludeProtected": true,
  "excludeInternal": true,
  "hideGenerator": true,
  "name": "Squadventure API",
  "includeVersion": false,
  "exclude": [
    "**/node_modules/**",
    "packages/web/**",
    "packages/cli/**",
    "packages/world-gen/**"
  ],
  "skipErrorChecking": true,
  "navigationLinks": {
    "Wiki": "../wiki/Home.md",
    "GitHub": "https://github.com/ctonyperry/squadventure"
  }
}
